chimera_core/__init__.py
chimera_core/controller.py
chimera_core/exception.py
chimera_core/core/__init__.py
chimera_core/core/const.py
chimera_core/core/generic_types.py
chimera_core/core/manager/__base.py
chimera_core/core/manager/__dataset.py
chimera_core/core/manager/__init__.py
chimera_core/core/manager/const.py
chimera_core/core/manager/exception.py
chimera_core/core/manager/module.py
chimera_core/core/manager/port.py
chimera_core/core/manager/tester.py
chimera_core/core/manager/flow/__dataset.py
chimera_core/core/manager/flow/__init__.py
chimera_core/core/manager/flow/distributions/ __init__.py
chimera_core/core/manager/flow/distributions/__dataset.py
chimera_core/core/manager/flow/distributions/corruption.py
chimera_core/core/manager/flow/distributions/drop.py
chimera_core/core/manager/flow/distributions/duplication.py
chimera_core/core/manager/flow/distributions/latency_jitter.py
chimera_core/core/manager/flow/distributions/misordering.py
chimera_core/core/manager/flow/impairments/__base.py
chimera_core/core/manager/flow/impairments/__dataset.py
chimera_core/core/manager/flow/impairments/__init__.py
chimera_core/core/manager/flow/impairments/corruption.py
chimera_core/core/manager/flow/impairments/drop.py
chimera_core/core/manager/flow/impairments/duplication.py
chimera_core/core/manager/flow/impairments/exception.py
chimera_core/core/manager/flow/impairments/latency_jitter.py
chimera_core/core/manager/flow/impairments/misordering.py
chimera_core/core/manager/flow/impairments/policer.py
chimera_core/core/manager/flow/impairments/shaper.py
chimera_core/core/manager/flow/shadow_filter/__dataset.py
chimera_core/core/manager/flow/shadow_filter/__init__.py
chimera_core/core/manager/flow/shadow_filter/basic_mode.py
chimera_core/core/manager/flow/shadow_filter/extended_mode.py
chimera_core/core/messenger/__init__.py
chimera_core/core/messenger/handler.py
chimera_core/core/messenger/misc.py
chimera_core/core/messenger/pipe.py
chimera_core/core/resources/__init__.py
chimera_core-1.0.3.dist-info/LICENSE
chimera_core-1.0.3.dist-info/METADATA
chimera_core-1.0.3.dist-info/WHEEL
chimera_core-1.0.3.dist-info/top_level.txt
chimera_core-1.0.3.dist-info/RECORD
