Metadata-Version: 2.1
Name: chimera-core
Version: 1.0.3
Summary: Xena OpenAutomation - Chimera Core, for network impairment test configuration, integration, and development.
Home-page: https://github.com/xenanetworks/chimera-core
Author: Frank Chen, Leonard Yu
Author-email: fch@xenanetworks.com, hyu@xenanewtorks.com
Maintainer: Xena Networks
Maintainer-email: support@xenanetworks.com
License: Apache 2.0
Classifier: Development Status :: 5 - Production/Stable
Classifier: Intended Audience :: Developers
Classifier: Topic :: Software Development :: Libraries :: Application Frameworks
Classifier: License :: OSI Approved :: Apache Software License
Classifier: Programming Language :: Python :: 3.8
Classifier: Programming Language :: Python :: 3.9
Classifier: Programming Language :: Python :: 3.10
Classifier: Programming Language :: Python :: 3.11
Requires-Python: >=3.8.9
License-File: LICENSE
Requires-Dist: xoa_driver>=2.1.3
Requires-Dist: pydantic
Requires-Dist: loguru
